eule/__init__.py
eule/core.py
eule/operations.py
eule/types.py
eule/utils.py
eule/validators.py
eule-1.3.1.dist-info/METADATA
eule-1.3.1.dist-info/WHEEL
eule-1.3.1.dist-info/licenses/LICENSE
eule-1.3.1.dist-info/RECORD
