Metadata-Version: 2.3
Name: eule
Version: 1.3.1
Summary: Euler diagrams in python
Project-URL: homepage, https://pypi.org/project/eule/
Project-URL: repository, https://github.com/trouchet/eule
Author-email: Bruno Peixoto <brunolnetto@gmail.com>
Maintainer-email: Bruno Peixoto <brunolnetto@gmail.com>
License: MIT License
Keywords: euler-diagram,sets
Classifier: Development Status :: 5 - Production/Stable
Classifier: Intended Audience :: Developers
Classifier: License :: OSI Approved :: MIT License
Classifier: Natural Language :: English
Classifier: Programming Language :: Python
Requires-Python: >=3.9
Requires-Dist: numpy>2.0.0
Provides-Extra: build
Requires-Dist: mypy>=0.991; extra == 'build'
Requires-Dist: wheel>=0.38.4; extra == 'build'
Provides-Extra: docs
Requires-Dist: docutils>=0.18.1; extra == 'docs'
Requires-Dist: sphinx-rtd-theme>=1.2.0; extra == 'docs'
Requires-Dist: sphinx>=6.0.0; extra == 'docs'
Requires-Dist: sphinxcontrib-serializinghtml>=1.1.5; extra == 'docs'
Requires-Dist: sphinxcontrib-websupport>=1.2.4; extra == 'docs'
Requires-Dist: toml>=0.10.2; extra == 'docs'
Requires-Dist: types-toml>=0.10.8.5; extra == 'docs'
Provides-Extra: lint
Requires-Dist: black<25.0,>=22.12; extra == 'lint'
Requires-Dist: isort>=5.11.4; extra == 'lint'
Requires-Dist: pre-commit>=2.20.0; extra == 'lint'
Requires-Dist: pylint>=2.15.9; extra == 'lint'
Requires-Dist: ruff>=0.0.217; extra == 'lint'
Provides-Extra: test
Requires-Dist: coverage>=7.0; extra == 'test'
Requires-Dist: pytest-cov>=4.0.0; extra == 'test'
Requires-Dist: pytest-timer>=1.0.0; extra == 'test'
Requires-Dist: pytest-watch>=4.2.0; extra == 'test'
Requires-Dist: pytest>=7.2.0; extra == 'test'
Requires-Dist: types-mock>=4.0.15.2; extra == 'test'
Requires-Dist: watchdog>=3.0.0; extra == 'test'
